silverstrike/__init__.py
silverstrike/admin.py
silverstrike/api.py
silverstrike/apps.py
silverstrike/forms.py
silverstrike/lib.py
silverstrike/models.py
silverstrike/urls.py
silverstrike/locale/da/LC_MESSAGES/django.mo
silverstrike/locale/da/LC_MESSAGES/django.po
silverstrike/locale/de/LC_MESSAGES/django.mo
silverstrike/locale/de/LC_MESSAGES/django.po
silverstrike/locale/en/LC_MESSAGES/django.mo
silverstrike/locale/en/LC_MESSAGES/django.po
silverstrike/locale/es/LC_MESSAGES/django.mo
silverstrike/locale/es/LC_MESSAGES/django.po
silverstrike/locale/fil/LC_MESSAGES/django.mo
silverstrike/locale/fil/LC_MESSAGES/django.po
silverstrike/locale/fr/LC_MESSAGES/django.mo
silverstrike/locale/fr/LC_MESSAGES/django.po
silverstrike/locale/id/LC_MESSAGES/django.mo
silverstrike/locale/id/LC_MESSAGES/django.po
silverstrike/locale/it/LC_MESSAGES/django.mo
silverstrike/locale/it/LC_MESSAGES/django.po
silverstrike/locale/nl/LC_MESSAGES/django.mo
silverstrike/locale/nl/LC_MESSAGES/django.po
silverstrike/locale/no/LC_MESSAGES/django.mo
silverstrike/locale/no/LC_MESSAGES/django.po
silverstrike/locale/pl/LC_MESSAGES/django.mo
silverstrike/locale/pl/LC_MESSAGES/django.po
silverstrike/locale/pt/LC_MESSAGES/django.mo
silverstrike/locale/pt/LC_MESSAGES/django.po
silverstrike/locale/ru/LC_MESSAGES/django.mo
silverstrike/locale/ru/LC_MESSAGES/django.po
silverstrike/locale/sv/LC_MESSAGES/django.mo
silverstrike/locale/sv/LC_MESSAGES/django.po
silverstrike/locale/tr/LC_MESSAGES/django.mo
silverstrike/locale/tr/LC_MESSAGES/django.po
silverstrike/locale/zh_CN/LC_MESSAGES/django.mo
silverstrike/locale/zh_CN/LC_MESSAGES/django.po
silverstrike/locale/zh_TW/LC_MESSAGES/django.mo
silverstrike/locale/zh_TW/LC_MESSAGES/django.po
silverstrike/management/__init__.py
silverstrike/management/commands/__init__.py
silverstrike/management/commands/createtestdata.py
silverstrike/management/commands/exporttransactions.py
silverstrike/management/commands/importfireflydata.py
silverstrike/migrations/0001_initial.py
silverstrike-0.1.4.dist-info/LICENSE
silverstrike-0.1.4.dist-info/METADATA
silverstrike-0.1.4.dist-info/WHEEL
silverstrike-0.1.4.dist-info/top_level.txt
silverstrike-0.1.4.dist-info/RECORD
