Metadata-Version: 2.1
Name: silverstrike
Version: 0.1.4
Summary: Django webapp to manage personal finances
Home-page: https://github.com/agstrike/silverstrike
Author: Simon Hanna
License: MIT
Keywords: finance django money money-manager
Platform: UNKNOWN
Classifier: Development Status :: 3 - Alpha
Classifier: Framework :: Django
Classifier: Framework :: Django :: 2.0
Classifier: Intended Audience :: End Users/Desktop
Classifier: License :: OSI Approved :: MIT License
Classifier: Operating System :: POSIX
Classifier: Programming Language :: Python :: 3
Classifier: Programming Language :: Python :: 3.4
Classifier: Programming Language :: Python :: 3.5
Classifier: Programming Language :: Python :: 3.6
Requires-Python: >=3.4
Requires-Dist: django (<3.0,>=2.0)
Requires-Dist: djangorestframework (<3.8)
Requires-Dist: django-widgets-improved
Requires-Dist: django-allauth
Requires-Dist: python-dateutil
